{
  "as_of": "2025-10-12",
  "exchange": "Wealthsimple Crypto (non-registered)",
  "cash_available_cad": 15.0,
  "constraints": {
    "max_positions": 10,
    "max_weight_per_position": 0.2,
    "min_trade_size_cad": 1.0
  },
  "fractional_allowed": true,
  "order_mode": "market_only",
  "fee_rate": 0.02,
  "holdings": [
    {
      "symbol": "AVAX",
      "amount": 0.110013,
      "avg_cost_cad": 31.3629,
      "market_price_cad": 31.22,
      "effective_buy_price_cad": 31.8444,
      "effective_sell_price_cad": 30.5956
    },
    {
      "symbol": "BNB",
      "amount": 0.00825,
      "avg_cost_cad": 1421.52,
      "market_price_cad": 1832.83,
      "effective_buy_price_cad": 1869.4866,
      "effective_sell_price_cad": 1796.1734
    },
    {
      "symbol": "CELO",
      "amount": 24.908519,
      "avg_cost_cad": 0.56,
      "market_price_cad": 0.413558,
      "effective_buy_price_cad": 0.421829,
      "effective_sell_price_cad": 0.405287
    },
    {
      "symbol": "DOGE",
      "amount": 11.707648,
      "avg_cost_cad": 0.3467,
      "market_price_cad": 0.292451,
      "effective_buy_price_cad": 0.2983,
      "effective_sell_price_cad": 0.286602
    },
    {
      "symbol": "DOT",
      "amount": 0.36,
      "avg_cost_cad": 5.72,
      "market_price_cad": 4.55,
      "effective_buy_price_cad": 4.641,
      "effective_sell_price_cad": 4.459
    },
    {
      "symbol": "ENA",
      "amount": 0.98,
      "avg_cost_cad": 1.06,
      "market_price_cad": 0.571726,
      "effective_buy_price_cad": 0.583161,
      "effective_sell_price_cad": 0.560291
    },
    {
      "symbol": "MOODENG",
      "amount": 19.227765,
      "avg_cost_cad": 0.298,
      "market_price_cad": 0.173941,
      "effective_buy_price_cad": 0.17742,
      "effective_sell_price_cad": 0.170462
    },
    {
      "symbol": "SNX",
      "amount": 11.210797,
      "avg_cost_cad": 1.46,
      "market_price_cad": 2.48,
      "effective_buy_price_cad": 2.5296,
      "effective_sell_price_cad": 2.4304
    },
    {
      "symbol": "WLD",
      "amount": 2.026621,
      "avg_cost_cad": 1.8317,
      "market_price_cad": 1.39,
      "effective_buy_price_cad": 1.4178,
      "effective_sell_price_cad": 1.3622
    }
  ],
  "candidates": [
    {
      "id": "bitcoin",
      "symbol": "BTC",
      "name": "Bitcoin",
      "price_cad": 161305.0,
      "pct_change_1w": -6.787941209599256,
      "vol_24h": 128373590372.0,
      "bucket": "up",
      "effective_buy_price_cad": 164531.1,
      "effective_sell_price_cad": 158078.9
    },
    {
      "id": "ethereum",
      "symbol": "ETH",
      "name": "Ethereum",
      "price_cad": 5821.09,
      "pct_change_1w": -8.054474700500673,
      "vol_24h": 79586801980.0,
      "bucket": "up",
      "effective_buy_price_cad": 5937.5118,
      "effective_sell_price_cad": 5704.6682
    },
    {
      "id": "usd-coin",
      "symbol": "USDC",
      "name": "USDC",
      "price_cad": 1.4,
      "pct_change_1w": 0.29917477771213213,
      "vol_24h": 23571165202.0,
      "bucket": "up",
      "effective_buy_price_cad": 1.428,
      "effective_sell_price_cad": 1.372
    },
    {
      "id": "ripple",
      "symbol": "XRP",
      "name": "XRP",
      "price_cad": 3.6,
      "pct_change_1w": -13.386808432106553,
      "vol_24h": 13527214912.0,
      "bucket": "up",
      "effective_buy_price_cad": 3.672,
      "effective_sell_price_cad": 3.528
    },
    {
      "id": "binancecoin",
      "symbol": "BNB",
      "name": "BNB",
      "price_cad": 1832.83,
      "pct_change_1w": 11.477031451309744,
      "vol_24h": 13169522231.0,
      "bucket": "up",
      "effective_buy_price_cad": 1869.4866,
      "effective_sell_price_cad": 1796.1734
    },
    {
      "id": "chainlink",
      "symbol": "LINK",
      "name": "Chainlink",
      "price_cad": 26.83,
      "pct_change_1w": -12.117988835778355,
      "vol_24h": 1898419232.0,
      "bucket": "up",
      "effective_buy_price_cad": 27.3666,
      "effective_sell_price_cad": 26.2934
    },
    {
      "id": "pancakeswap-token",
      "symbol": "CAKE",
      "name": "PancakeSwap",
      "price_cad": 4.76,
      "pct_change_1w": 1.3224772699173206,
      "vol_24h": 930063424.0,
      "bucket": "up",
      "effective_buy_price_cad": 4.8552,
      "effective_sell_price_cad": 4.6648
    },
    {
      "id": "aave",
      "symbol": "AAVE",
      "name": "Aave",
      "price_cad": 349.37,
      "pct_change_1w": -12.486294110664202,
      "vol_24h": 803576586.0,
      "bucket": "up",
      "effective_buy_price_cad": 356.3574,
      "effective_sell_price_cad": 342.3826
    },
    {
      "id": "havven",
      "symbol": "SNX",
      "name": "Synthetix",
      "price_cad": 2.48,
      "pct_change_1w": 54.80209789307897,
      "vol_24h": 737386752.0,
      "bucket": "up",
      "effective_buy_price_cad": 2.5296,
      "effective_sell_price_cad": 2.4304
    },
    {
      "id": "bitcoin-cash",
      "symbol": "BCH",
      "name": "Bitcoin Cash",
      "price_cad": 757.99,
      "pct_change_1w": -9.228616097778303,
      "vol_24h": 488397269.0,
      "bucket": "up",
      "effective_buy_price_cad": 773.1498,
      "effective_sell_price_cad": 742.8302
    },
    {
      "id": "ondo-finance",
      "symbol": "ONDO",
      "name": "Ondo",
      "price_cad": 1.13,
      "pct_change_1w": -11.653350257278465,
      "vol_24h": 365995833.0,
      "bucket": "up",
      "effective_buy_price_cad": 1.1526,
      "effective_sell_price_cad": 1.1074
    },
    {
      "id": "ethereum-classic",
      "symbol": "ETC",
      "name": "Ethereum Classic",
      "price_cad": 23.65,
      "pct_change_1w": -13.305691885052923,
      "vol_24h": 281481982.0,
      "bucket": "up",
      "effective_buy_price_cad": 24.123,
      "effective_sell_price_cad": 23.177
    },
    {
      "id": "algorand",
      "symbol": "ALGO",
      "name": "Algorand",
      "price_cad": 0.282431,
      "pct_change_1w": -7.619898256954405,
      "vol_24h": 171117113.0,
      "bucket": "up",
      "effective_buy_price_cad": 0.28808,
      "effective_sell_price_cad": 0.276782
    },
    {
      "id": "morpho",
      "symbol": "MORPHO",
      "name": "Morpho",
      "price_cad": 2.78,
      "pct_change_1w": 7.473401834200205,
      "vol_24h": 153612174.0,
      "bucket": "up",
      "effective_buy_price_cad": 2.8356,
      "effective_sell_price_cad": 2.7244
    },
    {
      "id": "basic-attention-token",
      "symbol": "BAT",
      "name": "Basic Attention",
      "price_cad": 0.244424,
      "pct_change_1w": 18.632144108699855,
      "vol_24h": 93047979.0,
      "bucket": "up",
      "effective_buy_price_cad": 0.249312,
      "effective_sell_price_cad": 0.239536
    },
    {
      "id": "quant-network",
      "symbol": "QNT",
      "name": "Quant",
      "price_cad": 125.45,
      "pct_change_1w": -11.908375265644306,
      "vol_24h": 46094302.0,
      "bucket": "up",
      "effective_buy_price_cad": 127.959,
      "effective_sell_price_cad": 122.941
    },
    {
      "id": "syrup",
      "symbol": "SYRUP",
      "name": "Maple Finance",
      "price_cad": 0.515585,
      "pct_change_1w": -10.256038044406674,
      "vol_24h": 44594638.0,
      "bucket": "up",
      "effective_buy_price_cad": 0.525897,
      "effective_sell_price_cad": 0.505273
    },
    {
      "id": "tezos",
      "symbol": "XTZ",
      "name": "Tezos",
      "price_cad": 0.886965,
      "pct_change_1w": -10.586833797286463,
      "vol_24h": 36569222.0,
      "bucket": "up",
      "effective_buy_price_cad": 0.904704,
      "effective_sell_price_cad": 0.869226
    },
    {
      "id": "yearn-finance",
      "symbol": "YFI",
      "name": "yearn.finance",
      "price_cad": 6803.29,
      "pct_change_1w": -10.4696565459706,
      "vol_24h": 30176084.0,
      "bucket": "up",
      "effective_buy_price_cad": 6939.3558,
      "effective_sell_price_cad": 6667.2242
    },
    {
      "id": "helium",
      "symbol": "HNT",
      "name": "Helium",
      "price_cad": 3.16,
      "pct_change_1w": -10.0531405201121,
      "vol_24h": 20635617.0,
      "bucket": "up",
      "effective_buy_price_cad": 3.2232,
      "effective_sell_price_cad": 3.0968
    },
    {
      "id": "ethena",
      "symbol": "ENA",
      "name": "Ethena",
      "price_cad": 0.571726,
      "pct_change_1w": -29.908963391858638,
      "vol_24h": 1023350407.0,
      "bucket": "down",
      "effective_buy_price_cad": 0.583161,
      "effective_sell_price_cad": 0.560291
    },
    {
      "id": "world-liberty-financial",
      "symbol": "WLFI",
      "name": "World Liberty Financial",
      "price_cad": 0.198464,
      "pct_change_1w": -28.809092770952212,
      "vol_24h": 576308496.0,
      "bucket": "down",
      "effective_buy_price_cad": 0.202433,
      "effective_sell_price_cad": 0.194495
    },
    {
      "id": "dogwifcoin",
      "symbol": "WIF",
      "name": "dogwifhat",
      "price_cad": 0.768607,
      "pct_change_1w": -27.989526134998528,
      "vol_24h": 487358424.0,
      "bucket": "down",
      "effective_buy_price_cad": 0.783979,
      "effective_sell_price_cad": 0.753235
    },
    {
      "id": "fartcoin",
      "symbol": "FARTCOIN",
      "name": "Fartcoin",
      "price_cad": 0.607683,
      "pct_change_1w": -35.25535992479453,
      "vol_24h": 354060356.0,
      "bucket": "down",
      "effective_buy_price_cad": 0.619837,
      "effective_sell_price_cad": 0.595529
    },
    {
      "id": "optimism",
      "symbol": "OP",
      "name": "Optimism",
      "price_cad": 0.676976,
      "pct_change_1w": -33.43620471460694,
      "vol_24h": 304131038.0,
      "bucket": "down",
      "effective_buy_price_cad": 0.690516,
      "effective_sell_price_cad": 0.663436
    },
    {
      "id": "filecoin",
      "symbol": "FIL",
      "name": "Filecoin",
      "price_cad": 2.31,
      "pct_change_1w": -29.38320407857159,
      "vol_24h": 290870874.0,
      "bucket": "down",
      "effective_buy_price_cad": 2.3562,
      "effective_sell_price_cad": 2.2638
    },
    {
      "id": "injective-protocol",
      "symbol": "INJ",
      "name": "Injective",
      "price_cad": 13.31,
      "pct_change_1w": -28.151489506711258,
      "vol_24h": 281905014.0,
      "bucket": "down",
      "effective_buy_price_cad": 13.5762,
      "effective_sell_price_cad": 13.0438
    },
    {
      "id": "eigenlayer",
      "symbol": "EIGEN",
      "name": "EigenCloud (prev. EigenLayer)",
      "price_cad": 1.89,
      "pct_change_1w": -28.2484804928472,
      "vol_24h": 264133980.0,
      "bucket": "down",
      "effective_buy_price_cad": 1.9278,
      "effective_sell_price_cad": 1.8522
    },
    {
      "id": "fetch-ai",
      "symbol": "FET",
      "name": "Artificial Superintelligence Alliance",
      "price_cad": 0.520199,
      "pct_change_1w": -35.872526233777634,
      "vol_24h": 230138365.0,
      "bucket": "down",
      "effective_buy_price_cad": 0.530603,
      "effective_sell_price_cad": 0.509795
    },
    {
      "id": "sonic-3",
      "symbol": "S",
      "name": "Sonic",
      "price_cad": 0.273308,
      "pct_change_1w": -28.99096063757023,
      "vol_24h": 215597020.0,
      "bucket": "down",
      "effective_buy_price_cad": 0.278774,
      "effective_sell_price_cad": 0.267842
    },
    {
      "id": "ether-fi",
      "symbol": "ETHFI",
      "name": "Ether.fi",
      "price_cad": 1.73,
      "pct_change_1w": -31.45962054361626,
      "vol_24h": 214602258.0,
      "bucket": "down",
      "effective_buy_price_cad": 1.7646,
      "effective_sell_price_cad": 1.6954
    },
    {
      "id": "celestia",
      "symbol": "TIA",
      "name": "Celestia",
      "price_cad": 1.47,
      "pct_change_1w": -29.417220968242486,
      "vol_24h": 161582986.0,
      "bucket": "down",
      "effective_buy_price_cad": 1.4994,
      "effective_sell_price_cad": 1.4406
    },
    {
      "id": "raydium",
      "symbol": "RAY",
      "name": "Raydium",
      "price_cad": 2.89,
      "pct_change_1w": -28.479842275760507,
      "vol_24h": 117061950.0,
      "bucket": "down",
      "effective_buy_price_cad": 2.9478,
      "effective_sell_price_cad": 2.8322
    },
    {
      "id": "wormhole",
      "symbol": "W",
      "name": "Wormhole",
      "price_cad": 0.115331,
      "pct_change_1w": -29.890152561300283,
      "vol_24h": 105001590.0,
      "bucket": "down",
      "effective_buy_price_cad": 0.117638,
      "effective_sell_price_cad": 0.113024
    },
    {
      "id": "peanut-the-squirrel",
      "symbol": "PNUT",
      "name": "Peanut the Squirrel",
      "price_cad": 0.211306,
      "pct_change_1w": -30.055376948006874,
      "vol_24h": 83187701.0,
      "bucket": "down",
      "effective_buy_price_cad": 0.215532,
      "effective_sell_price_cad": 0.20708
    },
    {
      "id": "popcat",
      "symbol": "POPCAT",
      "name": "Popcat",
      "price_cad": 0.228464,
      "pct_change_1w": -30.2326286847941,
      "vol_24h": 78723407.0,
      "bucket": "down",
      "effective_buy_price_cad": 0.233033,
      "effective_sell_price_cad": 0.223895
    },
    {
      "id": "grass",
      "symbol": "GRASS",
      "name": "Grass",
      "price_cad": 0.753604,
      "pct_change_1w": -36.78546137149677,
      "vol_24h": 70511513.0,
      "bucket": "down",
      "effective_buy_price_cad": 0.768676,
      "effective_sell_price_cad": 0.738532
    },
    {
      "id": "jito-governance-token",
      "symbol": "JTO",
      "name": "Jito",
      "price_cad": 1.6,
      "pct_change_1w": -29.007789165214014,
      "vol_24h": 62359669.0,
      "bucket": "down",
      "effective_buy_price_cad": 1.632,
      "effective_sell_price_cad": 1.568
    },
    {
      "id": "celo",
      "symbol": "CELO",
      "name": "Celo",
      "price_cad": 0.413558,
      "pct_change_1w": -38.741504247167306,
      "vol_24h": 41670995.0,
      "bucket": "down",
      "effective_buy_price_cad": 0.421829,
      "effective_sell_price_cad": 0.405287
    },
    {
      "id": "dydx-chain",
      "symbol": "DYDX",
      "name": "dYdX",
      "price_cad": 0.518884,
      "pct_change_1w": -38.863102278697966,
      "vol_24h": 31243509.0,
      "bucket": "down",
      "effective_buy_price_cad": 0.529262,
      "effective_sell_price_cad": 0.508506
    },
    {
      "id": "avalanche-2",
      "symbol": "AVAX",
      "name": "AVAX",
      "price_cad": 31.22,
      "pct_change_1w": null,
      "vol_24h": 0.0,
      "bucket": "holding",
      "effective_buy_price_cad": 31.8444,
      "effective_sell_price_cad": 30.5956
    },
    {
      "id": "dogecoin",
      "symbol": "DOGE",
      "name": "DOGE",
      "price_cad": 0.292451,
      "pct_change_1w": null,
      "vol_24h": 0.0,
      "bucket": "holding",
      "effective_buy_price_cad": 0.2983,
      "effective_sell_price_cad": 0.286602
    },
    {
      "id": "polkadot",
      "symbol": "DOT",
      "name": "DOT",
      "price_cad": 4.55,
      "pct_change_1w": null,
      "vol_24h": 0.0,
      "bucket": "holding",
      "effective_buy_price_cad": 4.641,
      "effective_sell_price_cad": 4.459
    },
    {
      "id": "moo-deng",
      "symbol": "MOODENG",
      "name": "MOODENG",
      "price_cad": 0.173941,
      "pct_change_1w": null,
      "vol_24h": 0.0,
      "bucket": "holding",
      "effective_buy_price_cad": 0.17742,
      "effective_sell_price_cad": 0.170462
    },
    {
      "id": "worldcoin-wld",
      "symbol": "WLD",
      "name": "WLD",
      "price_cad": 1.39,
      "pct_change_1w": null,
      "vol_24h": 0.0,
      "bucket": "holding",
      "effective_buy_price_cad": 1.4178,
      "effective_sell_price_cad": 1.3622
    }
  ]
}